helper_auth/__init__.py
helper_auth-0.8.0.dist-info/LICENSE
helper_auth-0.8.0.dist-info/METADATA
helper_auth-0.8.0.dist-info/WHEEL
helper_auth-0.8.0.dist-info/RECORD
