Metadata-Version: 2.1
Name: helper-auth
Version: 0.8.0
Summary: Request authentication using existing credential helpers.
Home-page: https://github.com/mportesdev/helper-auth
License: MIT
Keywords: http,requests,credentials
Author: Michal Porteš
Author-email: michalportes1@gmail.com
Requires-Python: >=3.8,<4.0
Classifier: Development Status :: 4 - Beta
Classifier: License :: OSI Approved :: MIT License
Classifier: Operating System :: OS Independent
Classifier: Programming Language :: Python :: 3
Classifier: Programming Language :: Python :: 3.8
Classifier: Programming Language :: Python :: 3.9
Classifier: Programming Language :: Python :: 3.10
Classifier: Programming Language :: Python :: 3.11
